innocuous/Endpoint.py
innocuous/MagicObj.py
innocuous/__init__.py
innocuous_magic-1.7.5.post9.dist-info/METADATA
innocuous_magic-1.7.5.post9.dist-info/WHEEL
innocuous_magic-1.7.5.post9.dist-info/top_level.txt
innocuous_magic-1.7.5.post9.dist-info/RECORD
