Metadata-Version: 2.1
Name: innocuous-magic
Version: 1.7.5.post9
Summary: innocuous library
Requires-Dist: boto3
Requires-Dist: torch (==1.8.0)
Requires-Dist: ray (==1.4.1)
Requires-Dist: ray[default] (==1.4.1)
Requires-Dist: ray[tune] (==1.4.1)
Requires-Dist: tensorflow (==2.4.1)
Requires-Dist: azure-storage-blob (==12.8.1)
Requires-Dist: colorlog
Requires-Dist: protobuf (==3.20.0)
Requires-Dist: lazy-import
